{
    "backpacks": {
        "0": {
            "capacity": 0.0
        },
        "1": {
            "capacity": 19.0
        },
        "2": {
            "capacity": 1.0
        },
        "3": {
            "capacity": 10.0
        },
        "4": {
            "capacity": 19.0
        },
        "5": {
            "capacity": 2.0
        },
        "6": {
            "capacity": 19.0
        },
        "7": {
            "capacity": 5.0
        },
        "8": {
            "capacity": 13.0
        },
        "9": {
            "capacity": 13.0
        },
        "10": {
            "capacity": 8.0
        }
    },
    "items": {
        "0": {
            "weight": 20.0,
            "value": 84.0
        },
        "1": {
            "weight": 15.0,
            "value": 65.0
        },
        "2": {
            "weight": 12.0,
            "value": 98.0
        },
        "3": {
            "weight": 19.0,
            "value": 98.0
        },
        "4": {
            "weight": 9.0,
            "value": 53.0
        },
        "5": {
            "weight": 16.0,
            "value": 91.0
        },
        "6": {
            "weight": 10.0,
            "value": 4.0
        },
        "7": {
            "weight": 17.0,
            "value": 26.0
        },
        "8": {
            "weight": 13.0,
            "value": 64.0
        },
        "9": {
            "weight": 18.0,
            "value": 89.0
        },
        "10": {
            "weight": 11.0,
            "value": 6.0
        },
        "11": {
            "weight": 3.0,
            "value": 19.0
        },
        "12": {
            "weight": 15.0,
            "value": 89.0
        },
        "13": {
            "weight": 15.0,
            "value": 52.0
        },
        "14": {
            "weight": 4.0,
            "value": 10.0
        },
        "15": {
            "weight": 7.0,
            "value": 85.0
        },
        "16": {
            "weight": 10.0,
            "value": 99.0
        },
        "17": {
            "weight": 18.0,
            "value": 86.0
        },
        "18": {
            "weight": 1.0,
            "value": 55.0
        },
        "19": {
            "weight": 20.0,
            "value": 54.0
        }
    }
}